{
    "text": "\u00ab Ses yeux sont comme ceux de sa m\u00e8re, mais les siens riaient toujours, \u00bb dit-il. \u00ab On dit que M. Craven ne supporte pas de le voir \u00e9veill\u00e9 \u00e0 cause de \u00e7a. \u00bb",
    "language_code": "fra",
    "language_probability": 1.0,
    "words": [
        {
            "text": "Ses",
            "start": 0.14,
            "end": 0.339,
            "type": "word",
            "speaker_id": null
        },
        {
            "text": " ",
            "start": 0.339,
            "end": 0.399,
            "type": "spacing",
            "speaker_id": null
        },
        {
            "text": "yeux",
            "start": 0.399,
            "end": 0.56,
            "type": "word",
            "speaker_id": null
        },
        {
            "text": " ",
            "start": 0.56,
            "end": 0.56,
            "type": "spacing",
            "speaker_id": null
        },
        {
            "text": "sont",
            "start": 0.56,
            "end": 0.759,
            "type": "word",
            "speaker_id": null
        },
        {
            "text": " ",
            "start": 0.759,
            "end": 0.759,
            "type": "spacing",
            "speaker_id": null
        },
        {
            "text": "comme",
            "start": 0.759,
            "end": 0.979,
            "type": "word",
            "speaker_id": null
        },
        {
            "text": " ",
            "start": 0.979,
            "end": 0.979,
            "type": "spacing",
            "speaker_id": null
        },
        {
            "text": "ceux",
            "start": 0.979,
            "end": 1.139,
            "type": "word",
            "speaker_id": null
        },
        {
            "text": " ",
            "start": 1.139,
            "end": 1.139,
            "type": "spacing",
            "speaker_id": null
        },
        {
            "text": "de",
            "start": 1.139,
            "end": 1.279,
            "type": "word",
            "speaker_id": null
        },
        {
            "text": " ",
            "start": 1.279,
            "end": 1.279,
            "type": "spacing",
            "speaker_id": null
        },
        {
            "text": "sa",
            "start": 1.279,
            "end": 1.459,
            "type": "word",
            "speaker_id": null
        },
        {
            "text": " ",
            "start": 1.459,
            "end": 1.48,
            "type": "spacing",
            "speaker_id": null
        },
        {
            "text": "m\u00e8re,",
            "start": 1.48,
            "end": 1.84,
            "type": "word",
            "speaker_id": null
        },
        {
            "text": " ",
            "start": 1.84,
            "end": 2.079,
            "type": "spacing",
            "speaker_id": null
        },
        {
            "text": "mais",
            "start": 2.079,
            "end": 2.179,
            "type": "word",
            "speaker_id": null
        },
        {
            "text": " ",
            "start": 2.179,
            "end": 2.2,
            "type": "spacing",
            "speaker_id": null
        },
        {
            "text": "les",
            "start": 2.2,
            "end": 2.399,
            "type": "word",
            "speaker_id": null
        },
        {
            "text": " ",
            "start": 2.399,
            "end": 2.399,
            "type": "spacing",
            "speaker_id": null
        },
        {
            "text": "siens",
            "start": 2.399,
            "end": 2.639,
            "type": "word",
            "speaker_id": null
        },
        {
            "text": " ",
            "start": 2.639,
            "end": 2.639,
            "type": "spacing",
            "speaker_id": null
        },
        {
            "text": "riaient",
            "start": 2.639,
            "end": 3.159,
            "type": "word",
            "speaker_id": null
        },
        {
            "text": " ",
            "start": 3.159,
            "end": 3.159,
            "type": "spacing",
            "speaker_id": null
        },
        {
            "text": "toujours,",
            "start": 3.159,
            "end": 3.759,
            "type": "word",
            "speaker_id": null
        },
        {
            "text": " ",
            "start": 3.759,
            "end": 4.039,
            "type": "spacing",
            "speaker_id": null
        },
        {
            "text": "dit-il.",
            "start": 4.039,
            "end": 4.639,
            "type": "word",
            "speaker_id": null
        },
        {
            "text": " ",
            "start": 4.639,
            "end": 5.139,
            "type": "spacing",
            "speaker_id": null
        },
        {
            "text": "\u00ab",
            "start": 5.139,
            "end": 5.299,
            "type": "word",
            "speaker_id": null
        },
        {
            "text": " ",
            "start": 5.299,
            "end": 5.299,
            "type": "spacing",
            "speaker_id": null
        },
        {
            "text": "On",
            "start": 5.299,
            "end": 5.459,
            "type": "word",
            "speaker_id": null
        },
        {
            "text": " ",
            "start": 5.459,
            "end": 5.46,
            "type": "spacing",
            "speaker_id": null
        },
        {
            "text": "dit",
            "start": 5.46,
            "end": 5.579,
            "type": "word",
            "speaker_id": null
        },
        {
            "text": " ",
            "start": 5.579,
            "end": 5.579,
            "type": "spacing",
            "speaker_id": null
        },
        {
            "text": "que",
            "start": 5.579,
            "end": 5.839,
            "type": "word",
            "speaker_id": null
        },
        {
            "text": " ",
            "start": 5.839,
            "end": 5.9,
            "type": "spacing",
            "speaker_id": null
        },
        {
            "text": "M.",
            "start": 5.9,
            "end": 6.319,
            "type": "word",
            "speaker_id": null
        },
        {
            "text": " ",
            "start": 6.319,
            "end": 6.339,
            "type": "spacing",
            "speaker_id": null
        },
        {
            "text": "Craven",
            "start": 6.339,
            "end": 6.479,
            "type": "word",
            "speaker_id": null
        },
        {
            "text": " ",
            "start": 6.479,
            "end": 6.48,
            "type": "spacing",
            "speaker_id": null
        },
        {
            "text": "ne",
            "start": 6.48,
            "end": 6.899,
            "type": "word",
            "speaker_id": null
        },
        {
            "text": " ",
            "start": 6.899,
            "end": 6.899,
            "type": "spacing",
            "speaker_id": null
        },
        {
            "text": "supporte",
            "start": 6.899,
            "end": 7.079,
            "type": "word",
            "speaker_id": null
        },
        {
            "text": " ",
            "start": 7.079,
            "end": 7.079,
            "type": "spacing",
            "speaker_id": null
        },
        {
            "text": "pas",
            "start": 7.079,
            "end": 7.139,
            "type": "word",
            "speaker_id": null
        },
        {
            "text": " ",
            "start": 7.139,
            "end": 7.139,
            "type": "spacing",
            "speaker_id": null
        },
        {
            "text": "de",
            "start": 7.139,
            "end": 7.219,
            "type": "word",
            "speaker_id": null
        },
        {
            "text": " ",
            "start": 7.219,
            "end": 7.239,
            "type": "spacing",
            "speaker_id": null
        },
        {
            "text": "le",
            "start": 7.239,
            "end": 7.419,
            "type": "word",
            "speaker_id": null
        },
        {
            "text": " ",
            "start": 7.419,
            "end": 7.44,
            "type": "spacing",
            "speaker_id": null
        },
        {
            "text": "voir",
            "start": 7.44,
            "end": 8.059,
            "type": "word",
            "speaker_id": null
        },
        {
            "text": " ",
            "start": 8.059,
            "end": 8.059,
            "type": "spacing",
            "speaker_id": null
        },
        {
            "text": "\u00e9veill\u00e9",
            "start": 8.059,
            "end": 8.199,
            "type": "word",
            "speaker_id": null
        },
        {
            "text": " ",
            "start": 8.199,
            "end": 8.199,
            "type": "spacing",
            "speaker_id": null
        },
        {
            "text": "\u00e0",
            "start": 8.199,
            "end": 8.42,
            "type": "word",
            "speaker_id": null
        },
        {
            "text": " ",
            "start": 8.42,
            "end": 8.42,
            "type": "spacing",
            "speaker_id": null
        },
        {
            "text": "cause",
            "start": 8.42,
            "end": 8.599,
            "type": "word",
            "speaker_id": null
        },
        {
            "text": " ",
            "start": 8.599,
            "end": 8.599,
            "type": "spacing",
            "speaker_id": null
        },
        {
            "text": "de",
            "start": 8.599,
            "end": 8.86,
            "type": "word",
            "speaker_id": null
        },
        {
            "text": " ",
            "start": 8.86,
            "end": 8.86,
            "type": "spacing",
            "speaker_id": null
        },
        {
            "text": "\u00e7a.",
            "start": 8.86,
            "end": 8.86,
            "type": "word",
            "speaker_id": null
        },
        {
            "text": "\u00bb",
            "start": 8.86,
            "end": 8.86,
            "type": "word",
            "speaker_id": null
        }
    ],
    "fixed": true
}