{
    "text": "« Peut-être, » dit-il. « Parlons du jardin. Ne veux-tu pas le voir ? »",
    "language_code": "fra",
    "language_probability": 1.0,
    "words": [
        {
            "text": "Peut-être",
            "start": 0.979,
            "end": 1.479,
            "type": "word",
            "speaker_id": null
        },
        {
            "text": "dit-il",
            "start": 2.339,
            "end": 2.439,
            "type": "word",
            "speaker_id": null
        },
        {
            "text": "Parlons",
            "start": 3.199,
            "end": 3.279,
            "type": "word",
            "speaker_id": null
        },
        {
            "text": "du",
            "start": 3.299,
            "end": 3.559,
            "type": "word",
            "speaker_id": null
        },
        {
            "text": "jardin",
            "start": 3.559,
            "end": 3.659,
            "type": "word",
            "speaker_id": null
        },
        {
            "text": "Ne",
            "start": 3.679,
            "end": 3.779,
            "type": "word",
            "speaker_id": null
        },
        {
            "text": "veux-tu",
            "start": 3.779,
            "end": 4.159,
            "type": "word",
            "speaker_id": null
        },
        {
            "text": "pas",
            "start": 4.159,
            "end": 4.159,
            "type": "word",
            "speaker_id": null
        },
        {
            "text": "le",
            "start": 4.159,
            "end": 4.159,
            "type": "word",
            "speaker_id": null
        },
        {
            "text": "voir",
            "start": 4.159,
            "end": 4.159,
            "type": "word",
            "speaker_id": null
        }
    ],
    "fixed": true
}