{
    "text": "\"Il a failli avoir une crise de col\u00e8re,\" soupira Marthe. \"Il n'arr\u00eatait pas de regarder l'horloge.\"",
    "language_code": "fra",
    "language_probability": 1.0,
    "words": [
        {
            "text": "Il",
            "start": 0.159,
            "end": 0.299,
            "type": "word",
            "speaker_id": null
        },
        {
            "text": " ",
            "start": 0.299,
            "end": 0.299,
            "type": "spacing",
            "speaker_id": null
        },
        {
            "text": "a",
            "start": 0.299,
            "end": 0.419,
            "type": "word",
            "speaker_id": null
        },
        {
            "text": " ",
            "start": 0.419,
            "end": 0.419,
            "type": "spacing",
            "speaker_id": null
        },
        {
            "text": "failli",
            "start": 0.419,
            "end": 0.659,
            "type": "word",
            "speaker_id": null
        },
        {
            "text": " ",
            "start": 0.659,
            "end": 0.74,
            "type": "spacing",
            "speaker_id": null
        },
        {
            "text": "avoir",
            "start": 0.74,
            "end": 0.899,
            "type": "word",
            "speaker_id": null
        },
        {
            "text": " ",
            "start": 0.899,
            "end": 0.899,
            "type": "spacing",
            "speaker_id": null
        },
        {
            "text": "une",
            "start": 0.899,
            "end": 1.039,
            "type": "word",
            "speaker_id": null
        },
        {
            "text": " ",
            "start": 1.039,
            "end": 1.039,
            "type": "spacing",
            "speaker_id": null
        },
        {
            "text": "crise",
            "start": 1.039,
            "end": 1.299,
            "type": "word",
            "speaker_id": null
        },
        {
            "text": " ",
            "start": 1.299,
            "end": 1.299,
            "type": "spacing",
            "speaker_id": null
        },
        {
            "text": "de",
            "start": 1.299,
            "end": 1.439,
            "type": "word",
            "speaker_id": null
        },
        {
            "text": " ",
            "start": 1.439,
            "end": 1.439,
            "type": "spacing",
            "speaker_id": null
        },
        {
            "text": "col\u00e8re,",
            "start": 1.439,
            "end": 1.939,
            "type": "word",
            "speaker_id": null
        },
        {
            "text": " ",
            "start": 1.939,
            "end": 2.18,
            "type": "spacing",
            "speaker_id": null
        },
        {
            "text": "soupira",
            "start": 2.18,
            "end": 2.599,
            "type": "word",
            "speaker_id": null
        },
        {
            "text": " ",
            "start": 2.599,
            "end": 2.599,
            "type": "spacing",
            "speaker_id": null
        },
        {
            "text": "Marthe.",
            "start": 2.599,
            "end": 3.019,
            "type": "word",
            "speaker_id": null
        },
        {
            "text": " ",
            "start": 3.019,
            "end": 3.339,
            "type": "spacing",
            "speaker_id": null
        },
        {
            "text": "Il",
            "start": 3.339,
            "end": 3.519,
            "type": "word",
            "speaker_id": null
        },
        {
            "text": " ",
            "start": 3.519,
            "end": 3.519,
            "type": "spacing",
            "speaker_id": null
        },
        {
            "text": "n'arr\u00eatait",
            "start": 3.519,
            "end": 3.96,
            "type": "word",
            "speaker_id": null
        },
        {
            "text": " ",
            "start": 3.96,
            "end": 3.98,
            "type": "spacing",
            "speaker_id": null
        },
        {
            "text": "pas",
            "start": 3.98,
            "end": 4.139,
            "type": "word",
            "speaker_id": null
        },
        {
            "text": " ",
            "start": 4.139,
            "end": 4.139,
            "type": "spacing",
            "speaker_id": null
        },
        {
            "text": "de",
            "start": 4.139,
            "end": 4.239,
            "type": "word",
            "speaker_id": null
        },
        {
            "text": " ",
            "start": 4.239,
            "end": 4.239,
            "type": "spacing",
            "speaker_id": null
        },
        {
            "text": "regarder",
            "start": 4.239,
            "end": 4.619,
            "type": "word",
            "speaker_id": null
        },
        {
            "text": " ",
            "start": 4.619,
            "end": 4.619,
            "type": "spacing",
            "speaker_id": null
        },
        {
            "text": "l'horloge.",
            "start": 4.619,
            "end": 5.279,
            "type": "word",
            "speaker_id": null
        }
    ],
    "fixed": true
}