{
    "text": "« D'où viens-tu ? » demanda-t-il.",
    "language_code": "fra",
    "language_probability": 1.0,
    "words": [
        {
            "text": "D'où",
            "start": 0.319,
            "end": 0.839,
            "type": "word",
            "speaker_id": null
        },
        {
            "text": "viens-tu",
            "start": 1.179,
            "end": 2.019,
            "type": "word",
            "speaker_id": null
        },
        {
            "text": "demanda-t-il",
            "start": 1.179,
            "end": 2.019,
            "type": "word",
            "speaker_id": null
        }
    ],
    "fixed": true
}