{
    "text": "Colin, rêveur, demanda : « Pensez-vous qu'il a été fait comme ça juste pour moi? »",
    "language_code": "fra",
    "language_probability": 1.0,
    "words": [
        {
            "text": "Colin",
            "start": 0.099,
            "end": 0.599,
            "type": "word",
            "speaker_id": null
        },
        {
            "text": "rêveur",
            "start": 0.599,
            "end": 1.059,
            "type": "word",
            "speaker_id": null
        },
        {
            "text": "demanda",
            "start": 1.059,
            "end": 1.579,
            "type": "word",
            "speaker_id": null
        },
        {
            "text": "Pensez-vous",
            "start": 2.039,
            "end": 2.46,
            "type": "word",
            "speaker_id": null
        },
        {
            "text": "qu'il",
            "start": 2.46,
            "end": 2.619,
            "type": "word",
            "speaker_id": null
        },
        {
            "text": "a",
            "start": 2.619,
            "end": 2.719,
            "type": "word",
            "speaker_id": null
        },
        {
            "text": "été",
            "start": 2.759,
            "end": 3.059,
            "type": "word",
            "speaker_id": null
        },
        {
            "text": "fait",
            "start": 3.059,
            "end": 3.179,
            "type": "word",
            "speaker_id": null
        },
        {
            "text": "comme",
            "start": 3.179,
            "end": 3.399,
            "type": "word",
            "speaker_id": null
        },
        {
            "text": "ça",
            "start": 3.399,
            "end": 3.619,
            "type": "word",
            "speaker_id": null
        },
        {
            "text": "juste",
            "start": 3.619,
            "end": 3.939,
            "type": "word",
            "speaker_id": null
        },
        {
            "text": "pour",
            "start": 3.939,
            "end": 4.139,
            "type": "word",
            "speaker_id": null
        },
        {
            "text": "moi",
            "start": 4.139,
            "end": 4.419,
            "type": "word",
            "speaker_id": null
        }
    ],
    "fixed": true
}