{
    "text": "\u00ab Il y a eu trop d'excitation. L'excitation n'est pas bonne pour toi. \u00bb, dit-il.",
    "language_code": "fra",
    "language_probability": 1.0,
    "words": [
        {
            "text": "Il",
            "start": 0.259,
            "end": 0.399,
            "type": "word",
            "speaker_id": null
        },
        {
            "text": " ",
            "start": 0.399,
            "end": 0.459,
            "type": "spacing",
            "speaker_id": null
        },
        {
            "text": "y",
            "start": 0.459,
            "end": 0.499,
            "type": "word",
            "speaker_id": null
        },
        {
            "text": " ",
            "start": 0.499,
            "end": 0.519,
            "type": "spacing",
            "speaker_id": null
        },
        {
            "text": "a",
            "start": 0.519,
            "end": 0.599,
            "type": "word",
            "speaker_id": null
        },
        {
            "text": " ",
            "start": 0.599,
            "end": 0.62,
            "type": "spacing",
            "speaker_id": null
        },
        {
            "text": "eu",
            "start": 0.62,
            "end": 0.699,
            "type": "word",
            "speaker_id": null
        },
        {
            "text": " ",
            "start": 0.699,
            "end": 0.779,
            "type": "spacing",
            "speaker_id": null
        },
        {
            "text": "trop",
            "start": 0.779,
            "end": 0.979,
            "type": "word",
            "speaker_id": null
        },
        {
            "text": " ",
            "start": 0.979,
            "end": 0.979,
            "type": "spacing",
            "speaker_id": null
        },
        {
            "text": "d'excitation.",
            "start": 0.979,
            "end": 1.779,
            "type": "word",
            "speaker_id": null
        },
        {
            "text": " ",
            "start": 1.779,
            "end": 2.059,
            "type": "spacing",
            "speaker_id": null
        },
        {
            "text": "L'excitation",
            "start": 2.059,
            "end": 2.679,
            "type": "word",
            "speaker_id": null
        },
        {
            "text": " ",
            "start": 2.679,
            "end": 2.679,
            "type": "spacing",
            "speaker_id": null
        },
        {
            "text": "n'est",
            "start": 2.679,
            "end": 2.879,
            "type": "word",
            "speaker_id": null
        },
        {
            "text": " ",
            "start": 2.879,
            "end": 2.899,
            "type": "spacing",
            "speaker_id": null
        },
        {
            "text": "pas",
            "start": 2.899,
            "end": 3.019,
            "type": "word",
            "speaker_id": null
        },
        {
            "text": " ",
            "start": 3.019,
            "end": 3.019,
            "type": "spacing",
            "speaker_id": null
        },
        {
            "text": "bonne",
            "start": 3.019,
            "end": 3.24,
            "type": "word",
            "speaker_id": null
        },
        {
            "text": " ",
            "start": 3.24,
            "end": 3.24,
            "type": "spacing",
            "speaker_id": null
        },
        {
            "text": "pour",
            "start": 3.24,
            "end": 3.419,
            "type": "word",
            "speaker_id": null
        },
        {
            "text": " ",
            "start": 3.419,
            "end": 3.419,
            "type": "spacing",
            "speaker_id": null
        },
        {
            "text": "toi.",
            "start": 3.419,
            "end": 3.739,
            "type": "word",
            "speaker_id": null
        },
        {
            "text": " ",
            "start": 3.739,
            "end": 4.099,
            "type": "spacing",
            "speaker_id": null
        },
        {
            "text": "dit-il.",
            "start": 4.099,
            "end": 4.679,
            "type": "word",
            "speaker_id": null
        }
    ],
    "fixed": true
}