{
    "text": "Marie se sentit contrariée. « S'ils souhaitaient que je le fasse, je ne le ferais pas. Qui souhaite que tu le fasses ? »",
    "language_code": "fra",
    "language_probability": 1.0,
    "words": [
        {
            "text": "Marie",
            "start": 0.099,
            "end": 0.399,
            "type": "word",
            "speaker_id": null
        },
        {
            "text": "se",
            "start": 0.399,
            "end": 0.539,
            "type": "word",
            "speaker_id": null
        },
        {
            "text": "sentit",
            "start": 0.56,
            "end": 0.859,
            "type": "word",
            "speaker_id": null
        },
        {
            "text": "contrariée",
            "start": 0.859,
            "end": 1.499,
            "type": "word",
            "speaker_id": null
        },
        {
            "text": "S'ils",
            "start": 1.979,
            "end": 2.199,
            "type": "word",
            "speaker_id": null
        },
        {
            "text": "souhaitaient",
            "start": 2.2,
            "end": 2.639,
            "type": "word",
            "speaker_id": null
        },
        {
            "text": "que",
            "start": 2.859,
            "end": 2.979,
            "type": "word",
            "speaker_id": null
        },
        {
            "text": "je",
            "start": 3.0,
            "end": 3.099,
            "type": "word",
            "speaker_id": null
        },
        {
            "text": "le",
            "start": 3.119,
            "end": 3.299,
            "type": "word",
            "speaker_id": null
        },
        {
            "text": "fasse",
            "start": 3.299,
            "end": 3.739,
            "type": "word",
            "speaker_id": null
        },
        {
            "text": "je",
            "start": 4.0,
            "end": 4.099,
            "type": "word",
            "speaker_id": null
        },
        {
            "text": "ne",
            "start": 4.139,
            "end": 4.219,
            "type": "word",
            "speaker_id": null
        },
        {
            "text": "le",
            "start": 4.239,
            "end": 4.319,
            "type": "word",
            "speaker_id": null
        },
        {
            "text": "ferai",
            "start": 4.38,
            "end": 4.699,
            "type": "word",
            "speaker_id": null
        },
        {
            "text": "pas",
            "start": 4.699,
            "end": 4.939,
            "type": "word",
            "speaker_id": null
        },
        {
            "text": "Qui",
            "start": 5.279,
            "end": 5.419,
            "type": "word",
            "speaker_id": null
        },
        {
            "text": "souhaite",
            "start": 5.46,
            "end": 5.739,
            "type": "word",
            "speaker_id": null
        },
        {
            "text": "que",
            "start": 5.739,
            "end": 5.819,
            "type": "word",
            "speaker_id": null
        },
        {
            "text": "tu",
            "start": 5.859,
            "end": 5.98,
            "type": "word",
            "speaker_id": null
        },
        {
            "text": "le",
            "start": 5.98,
            "end": 6.119,
            "type": "word",
            "speaker_id": null
        },
        {
            "text": "fasses",
            "start": 6.119,
            "end": 6.54,
            "type": "word",
            "speaker_id": null
        }
    ],
    "fixed": true
}