{
    "text": "Ils explorèrent, en chuchotant, découvrant des merveilles. Dickon lui montra des bourgeons sur des branches de rosiers et de nouvelles pousses vertes. Ils reniflèrent la terre, en riant doucement.",
    "language_code": "fra",
    "language_probability": 1.0,
    "words": [
        {
            "text": "Ils",
            "start": 0.079,
            "end": 0.319,
            "type": "word",
            "speaker_id": null
        },
        {
            "text": "explorèrent",
            "start": 0.34,
            "end": 1.159,
            "type": "word",
            "speaker_id": null
        },
        {
            "text": "en",
            "start": 1.599,
            "end": 1.74,
            "type": "word",
            "speaker_id": null
        },
        {
            "text": "chuchotant",
            "start": 1.799,
            "end": 2.499,
            "type": "word",
            "speaker_id": null
        },
        {
            "text": "découvrant",
            "start": 2.799,
            "end": 3.379,
            "type": "word",
            "speaker_id": null
        },
        {
            "text": "des",
            "start": 3.399,
            "end": 3.559,
            "type": "word",
            "speaker_id": null
        },
        {
            "text": "merveilles",
            "start": 3.579,
            "end": 4.219,
            "type": "word",
            "speaker_id": null
        },
        {
            "text": "Dickon",
            "start": 4.94,
            "end": 5.359,
            "type": "word",
            "speaker_id": null
        },
        {
            "text": "lui",
            "start": 5.38,
            "end": 5.519,
            "type": "word",
            "speaker_id": null
        },
        {
            "text": "montra",
            "start": 5.539,
            "end": 5.879,
            "type": "word",
            "speaker_id": null
        },
        {
            "text": "des",
            "start": 5.879,
            "end": 6.039,
            "type": "word",
            "speaker_id": null
        },
        {
            "text": "bourgeons",
            "start": 6.039,
            "end": 6.519,
            "type": "word",
            "speaker_id": null
        },
        {
            "text": "sur",
            "start": 6.519,
            "end": 6.679,
            "type": "word",
            "speaker_id": null
        },
        {
            "text": "des",
            "start": 6.699,
            "end": 6.819,
            "type": "word",
            "speaker_id": null
        },
        {
            "text": "branches",
            "start": 6.839,
            "end": 7.179,
            "type": "word",
            "speaker_id": null
        },
        {
            "text": "de",
            "start": 7.199,
            "end": 7.279,
            "type": "word",
            "speaker_id": null
        },
        {
            "text": "rosiers",
            "start": 7.299,
            "end": 7.799,
            "type": "word",
            "speaker_id": null
        },
        {
            "text": "et",
            "start": 8.099,
            "end": 8.219,
            "type": "word",
            "speaker_id": null
        },
        {
            "text": "de",
            "start": 8.22,
            "end": 8.319,
            "type": "word",
            "speaker_id": null
        },
        {
            "text": "nouvelles",
            "start": 8.359,
            "end": 8.719,
            "type": "word",
            "speaker_id": null
        },
        {
            "text": "pousses",
            "start": 8.72,
            "end": 9.039,
            "type": "word",
            "speaker_id": null
        },
        {
            "text": "vertes",
            "start": 9.039,
            "end": 9.56,
            "type": "word",
            "speaker_id": null
        },
        {
            "text": "Ils",
            "start": 10.119,
            "end": 10.259,
            "type": "word",
            "speaker_id": null
        },
        {
            "text": "reniflèrent",
            "start": 10.3,
            "end": 10.819,
            "type": "word",
            "speaker_id": null
        },
        {
            "text": "la",
            "start": 10.819,
            "end": 10.939,
            "type": "word",
            "speaker_id": null
        },
        {
            "text": "terre",
            "start": 11.019,
            "end": 11.399,
            "type": "word",
            "speaker_id": null
        },
        {
            "text": "en",
            "start": 11.92,
            "end": 12.079,
            "type": "word",
            "speaker_id": null
        },
        {
            "text": "riant",
            "start": 12.099,
            "end": 12.559,
            "type": "word",
            "speaker_id": null
        },
        {
            "text": "doucement",
            "start": 12.559,
            "end": 13.179,
            "type": "word",
            "speaker_id": null
        }
    ],
    "fixed": true
}